lord_ahrs_driver-0.1.0.dist-info/METADATA
lord_ahrs_driver-0.1.0.dist-info/WHEEL
lord_ahrs_driver/__init__.py
lord_ahrs_driver/lord_ahrs_driver.cpython-310-darwin.so
lord_ahrs_driver-0.1.0.dist-info/RECORD
